afpcli/__init__.py
afpcli-1.0.dev0.dist-info/DESCRIPTION.rst
afpcli-1.0.dev0.dist-info/METADATA
afpcli-1.0.dev0.dist-info/RECORD
afpcli-1.0.dev0.dist-info/WHEEL
afpcli-1.0.dev0.dist-info/metadata.json
afpcli-1.0.dev0.dist-info/namespace_packages.txt
afpcli-1.0.dev0.dist-info/top_level.txt
afpcli-1.0.dev0.dist-info/zip-safe
