Metadata-Version: 2.0
Name: afpcli
Version: 1.0.dev0
Summary: Placeholder for afp-cli in case someone misspells it
Home-page: UNKNOWN
Author: UNKNOWN
Author-email: UNKNOWN
License: UNKNOWN
Platform: UNKNOWN
Classifier: Development Status :: 3 - Alpha
Classifier: Programming Language :: Python
Requires-Dist: afp-cli
